{
  "states": {
    "dialogue": {
      "text": "Alchimista, cosa ti porta nella fucina dei Fabbri? Non abbiamo bisogno delle tue pozioni qui.",
      "type": "default",
      "choices": [
        {
          "next": "response",
          "text": "Passavo solo per un saluto, nulla di più."
        }
      ]
    },
    "response": {
      "text": "Un saluto, eh? Bene, ora che l'hai dato, puoi tornare ai tuoi alambicchi.",
      "choices": [
        {
          "next": "end",
          "text": "Buona giornata."
        }
      ],
      "type": "default"
    },
    "end": {
      "text": "",
      "type": "end_dialogue"
    }
  },
  "layout": {
    "type": "blabber:rpg"
  },
  "unskippable": false,
  "start_at": "dialogue"
}
